pycaprio/__init__.py
pycaprio/core/__init__.py
pycaprio/core/adapters/__init__.py
pycaprio/core/adapters/http_adapter.py
pycaprio/core/adapters/local_adapter.py
pycaprio/core/clients/__init__.py
pycaprio/core/clients/retryable_client.py
pycaprio/core/exceptions.py
pycaprio/core/interfaces/__init__.py
pycaprio/core/interfaces/adapter.py
pycaprio/core/interfaces/client.py
pycaprio/core/interfaces/schema.py
pycaprio/core/interfaces/types.py
pycaprio/core/mappings.py
pycaprio/core/objects/__init__.py
pycaprio/core/objects/annotation.py
pycaprio/core/objects/curation.py
pycaprio/core/objects/document.py
pycaprio/core/objects/project.py
pycaprio/core/pycaprio.py
pycaprio/core/schemas/__init__.py
pycaprio/core/schemas/annotation.py
pycaprio/core/schemas/curation.py
pycaprio/core/schemas/document.py
pycaprio/core/schemas/project.py
pycaprio/mappings.py
pycaprio/objects.py
pycaprio-0.3.1.dist-info/LICENSE
pycaprio-0.3.1.dist-info/METADATA
pycaprio-0.3.1.dist-info/WHEEL
pycaprio-0.3.1.dist-info/RECORD
