Metadata-Version: 2.3
Name: pycaprio
Version: 0.3.1
Summary: Python client for the INCEpTION annotation tool remote API
License: MIT
Author: The INCEpTION Project
Maintainer: Richard Eckart de Castilho
Requires-Python: >=3.9,<4.0
Classifier: License :: OSI Approved :: MIT License
Classifier: Programming Language :: Python :: 3
Classifier: Programming Language :: Python :: 3.9
Classifier: Programming Language :: Python :: 3.10
Classifier: Programming Language :: Python :: 3.11
Classifier: Programming Language :: Python :: 3.12
Classifier: Programming Language :: Python :: 3.13
Requires-Dist: requests (>=2.32.3,<3.0.0)
Requires-Dist: requests-toolbelt (>=1.0.0,<2.0.0)
Project-URL: Documentation, https://pycaprio.readthedocs.io
Project-URL: Repository, https://github.com/inception-project/pycaprio
